projects/alu8_rtl_to_gds/results/alu8_synth.v
/* Generated by Yosys 0.52 (git sha1 fee39a3284c90249e1d9684cf6944ffbbcbb8f90) */

(* top =  1  *)
(* src = "rtl/alu8.v:1.1-55.10" *)
module alu8(A, B, OP, Y, CARRY);
  wire _000_;
  wire _001_;
  wire _002_;
  wire _003_;
  wire _004_;
  wire _005_;
  wire _006_;
  wire _007_;
  wire _008_;
  wire _009_;
  wire _010_;
  wire _011_;
  wire _012_;
  wire _013_;
  wire _014_;
  wire _015_;
  wire _016_;
  wire _017_;
  wire _018_;
  wire _019_;
  wire _020_;
  wire _021_;
  wire _022_;
  wire _023_;
  wire _024_;
  wire _025_;
  wire _026_;
  wire _027_;
  wire _028_;
  wire _029_;
  wire _030_;
  wire _031_;
  wire _032_;
  wire _033_;
  wire _034_;
  wire _035_;
  wire _036_;
  wire _037_;
  wire _038_;
  wire _039_;
  wire _040_;
  wire _041_;
  wire _042_;
  wire _043_;
  wire _044_;
  wire _045_;
  wire _046_;
  wire _047_;
  wire _048_;
  wire _049_;
  wire _050_;
  wire _051_;
  wire _052_;
  wire _053_;
  wire _054_;
  wire _055_;
  wire _056_;
  wire _057_;
  wire _058_;
  wire _059_;
  wire _060_;
  wire _061_;
  wire _062_;
  wire _063_;
  wire _064_;
  wire _065_;
  wire _066_;
  wire _067_;
  wire _068_;
  wire _069_;
  wire _070_;
  wire _071_;
  wire _072_;
  wire _073_;
  wire _074_;
  wire _075_;
  wire _076_;
  wire _077_;
  wire _078_;
  wire _079_;
  wire _080_;
  wire _081_;
  wire _082_;
  wire _083_;
  wire _084_;
  wire _085_;
  wire _086_;
  wire _087_;
  wire _088_;
  wire _089_;
  wire _090_;
  wire _091_;
  wire _092_;
  wire _093_;
  wire _094_;
  wire _095_;
  wire _096_;
  wire _097_;
  wire _098_;
  wire _099_;
  wire _100_;
  wire _101_;
  wire _102_;
  wire _103_;
  wire _104_;
  wire _105_;
  wire _106_;
  wire _107_;
  wire _108_;
  wire _109_;
  wire _110_;
  wire _111_;
  wire _112_;
  wire _113_;
  wire _114_;
  wire _115_;
  wire _116_;
  wire _117_;
  wire _118_;
  wire _119_;
  wire _120_;
  wire _121_;
  wire _122_;
  wire _123_;
  wire _124_;
  wire _125_;
  wire _126_;
  wire _127_;
  wire _128_;
  wire _129_;
  wire _130_;
  wire _131_;
  wire _132_;
  wire _133_;
  wire _134_;
  wire _135_;
  wire _136_;
  wire _137_;
  wire _138_;
  wire _139_;
  wire _140_;
  wire _141_;
  wire _142_;
  wire _143_;
  wire _144_;
  wire _145_;
  wire _146_;
  wire _147_;
  wire _148_;
  wire _149_;
  wire _150_;
  wire _151_;
  wire _152_;
  wire _153_;
  wire _154_;
  wire _155_;
  wire _156_;
  wire _157_;
  wire _158_;
  wire _159_;
  wire _160_;
  wire _161_;
  wire _162_;
  wire _163_;
  wire _164_;
  wire _165_;
  wire _166_;
  wire _167_;
  wire _168_;
  wire _169_;
  wire _170_;
  wire _171_;
  wire _172_;
  wire _173_;
  wire _174_;
  wire _175_;
  wire _176_;
  wire _177_;
  wire _178_;
  wire _179_;
  wire _180_;
  wire _181_;
  wire _182_;
  wire _183_;
  wire _184_;
  wire _185_;
  wire _186_;
  wire _187_;
  wire _188_;
  wire _189_;
  wire _190_;
  wire _191_;
  wire _192_;
  wire _193_;
  wire _194_;
  wire _195_;
  wire _196_;
  wire _197_;
  wire _198_;
  wire _199_;
  wire _200_;
  wire _201_;
  wire _202_;
  wire _203_;
  wire _204_;
  wire _205_;
  wire _206_;
  wire _207_;
  wire _208_;
  wire _209_;
  (* src = "rtl/alu8.v:2.18-2.19" *)
  input [7:0] A;
  wire [7:0] A;
  (* src = "rtl/alu8.v:3.18-3.19" *)
  input [7:0] B;
  wire [7:0] B;
  (* src = "rtl/alu8.v:6.22-6.27" *)
  output CARRY;
  wire CARRY;
  (* src = "rtl/alu8.v:4.18-4.20" *)
  input [2:0] OP;
  wire [2:0] OP;
  (* src = "rtl/alu8.v:5.22-5.23" *)
  output [7:0] Y;
  wire [7:0] Y;
  assign _139_ = ~OP[0];
  assign _140_ = ~OP[1];
  assign _141_ = ~OP[2];
  assign _142_ = ~A[0];
  assign _143_ = ~A[1];
  assign _144_ = ~A[2];
  assign _145_ = ~A[3];
  assign _146_ = ~A[4];
  assign _147_ = ~A[5];
  assign _148_ = ~A[6];
  assign _149_ = ~A[7];
  assign _150_ = _149_ | B[7];
  assign _151_ = A[7] & B[7];
  assign _152_ = A[7] | B[7];
  assign _153_ = A[7] ^ B[7];
  assign _154_ = _148_ | B[6];
  assign _155_ = A[6] & B[6];
  assign _156_ = A[6] | B[6];
  assign _157_ = A[6] ^ B[6];
  assign _158_ = _147_ | B[5];
  assign _159_ = A[5] | B[5];
  assign _160_ = A[5] & B[5];
  assign _161_ = A[5] ^ B[5];
  assign _162_ = _146_ | B[4];
  assign _163_ = A[4] & B[4];
  assign _164_ = A[4] | B[4];
  assign _165_ = A[4] ^ B[4];
  assign _166_ = _145_ | B[3];
  assign _167_ = A[3] & B[3];
  assign _168_ = A[3] | B[3];
  assign _169_ = A[3] ^ B[3];
  assign _170_ = _144_ | B[2];
  assign _171_ = A[2] & B[2];
  assign _172_ = A[2] | B[2];
  assign _173_ = A[2] ^ B[2];
  assign _174_ = _143_ | B[1];
  assign _175_ = A[1] & B[1];
  assign _176_ = A[1] | B[1];
  assign _177_ = A[1] ^ B[1];
  assign _178_ = A[0] & B[0];
  assign _179_ = A[0] | B[0];
  assign _180_ = A[0] ^ B[0];
  assign _181_ = _142_ & B[0];
  assign _182_ = _177_ | _181_;
  assign _183_ = _174_ & _182_;
  assign _184_ = _173_ | _183_;
  assign _185_ = _170_ & _184_;
  assign _186_ = _169_ | _185_;
  assign _187_ = _166_ & _186_;
  assign _188_ = _165_ | _187_;
  assign _189_ = _162_ & _188_;
  assign _190_ = _161_ | _189_;
  assign _191_ = _158_ & _190_;
  assign _192_ = _157_ | _191_;
  assign _193_ = _154_ & _192_;
  assign _194_ = _153_ | _193_;
  assign _195_ = OP[0] & _140_;
  assign _196_ = _141_ & _195_;
  assign _197_ = _194_ & _196_;
  assign _198_ = _150_ & _197_;
  assign _199_ = _176_ & _178_;
  assign _200_ = _175_ | _199_;
  assign _201_ = _173_ & _200_;
  assign _202_ = _171_ | _201_;
  assign _203_ = _169_ & _202_;
  assign _204_ = _167_ | _203_;
  assign _205_ = _165_ & _204_;
  assign _206_ = _163_ | _205_;
  assign _207_ = _159_ & _206_;
  assign _208_ = _160_ | _207_;
  assign _209_ = _157_ & _208_;
  assign _000_ = _155_ | _209_;
  assign _001_ = _151_ | _000_;
  assign _002_ = _139_ & _140_;
  assign _003_ = _141_ & _002_;
  assign _004_ = _152_ & _003_;
  assign _005_ = _001_ & _004_;
  assign CARRY = _198_ | _005_;
  assign _006_ = _196_ | _002_;
  assign _007_ = _180_ & _006_;
  assign _008_ = OP[0] & OP[1];
  assign _009_ = _141_ & _008_;
  assign _010_ = _179_ & _009_;
  assign _011_ = OP[2] & _008_;
  assign _012_ = A[1] & _011_;
  assign _013_ = _010_ | _012_;
  assign _014_ = OP[2] & _195_;
  assign _015_ = _142_ & _014_;
  assign _016_ = _139_ & OP[1];
  assign _017_ = _141_ & _016_;
  assign _018_ = _178_ & _017_;
  assign _019_ = _015_ | _018_;
  assign _020_ = _013_ | _019_;
  assign Y[0] = _007_ | _020_;
  assign _021_ = _177_ ^ _181_;
  assign _022_ = _196_ & _021_;
  assign _023_ = _141_ & _178_;
  assign _024_ = _177_ ^ _023_;
  assign _025_ = _002_ & _024_;
  assign _026_ = A[2] & _011_;
  assign _027_ = OP[2] & _016_;
  assign _028_ = A[0] & _027_;
  assign _029_ = _176_ & _009_;
  assign _030_ = _143_ & _014_;
  assign _031_ = _175_ & _017_;
  assign _032_ = _028_ | _031_;
  assign _033_ = _026_ | _032_;
  assign _034_ = _030_ | _033_;
  assign _035_ = _025_ | _029_;
  assign _036_ = _022_ | _035_;
  assign Y[1] = _034_ | _036_;
  assign _037_ = _173_ & _183_;
  assign _038_ = ~_037_;
  assign _039_ = _184_ & _196_;
  assign _040_ = _038_ & _039_;
  assign _041_ = _173_ ^ _200_;
  assign _042_ = _003_ & _041_;
  assign _043_ = _171_ & _017_;
  assign _044_ = _172_ & _009_;
  assign _045_ = OP[2] & _002_;
  assign _046_ = _173_ & _045_;
  assign _047_ = _144_ & _014_;
  assign _048_ = A[1] & _027_;
  assign _049_ = A[3] & _011_;
  assign _050_ = _047_ | _048_;
  assign _051_ = _046_ | _050_;
  assign _052_ = _044_ | _049_;
  assign _053_ = _043_ | _052_;
  assign _054_ = _051_ | _053_;
  assign _055_ = _042_ | _054_;
  assign Y[2] = _040_ | _055_;
  assign _056_ = _169_ ^ _185_;
  assign _057_ = _196_ & _056_;
  assign _058_ = _169_ ^ _202_;
  assign _059_ = _003_ & _058_;
  assign _060_ = _168_ & _009_;
  assign _061_ = _169_ & _045_;
  assign _062_ = _060_ | _061_;
  assign _063_ = _145_ & _014_;
  assign _064_ = A[4] & _011_;
  assign _065_ = _063_ | _064_;
  assign _066_ = A[2] & _027_;
  assign _067_ = _167_ & _017_;
  assign _068_ = _066_ | _067_;
  assign _069_ = _065_ | _068_;
  assign _070_ = _062_ | _069_;
  assign _071_ = _059_ | _070_;
  assign Y[3] = _057_ | _071_;
  assign _072_ = _165_ ^ _187_;
  assign _073_ = _196_ & _072_;
  assign _074_ = _165_ ^ _204_;
  assign _075_ = _003_ & _074_;
  assign _076_ = _164_ & _009_;
  assign _077_ = _165_ & _045_;
  assign _078_ = _076_ | _077_;
  assign _079_ = _146_ & _014_;
  assign _080_ = _163_ & _017_;
  assign _081_ = _079_ | _080_;
  assign _082_ = A[3] & _027_;
  assign _083_ = A[5] & _011_;
  assign _084_ = _082_ | _083_;
  assign _085_ = _081_ | _084_;
  assign _086_ = _078_ | _085_;
  assign _087_ = _075_ | _086_;
  assign Y[4] = _073_ | _087_;
  assign _088_ = _161_ & _189_;
  assign _089_ = ~_088_;
  assign _090_ = _190_ & _196_;
  assign _091_ = _089_ & _090_;
  assign _092_ = _161_ ^ _206_;
  assign _093_ = _003_ & _092_;
  assign _094_ = _160_ & _017_;
  assign _095_ = A[4] & _027_;
  assign _096_ = _159_ & _009_;
  assign _097_ = _147_ & _014_;
  assign _098_ = A[6] & _011_;
  assign _099_ = _161_ & _045_;
  assign _100_ = _097_ | _098_;
  assign _101_ = _095_ | _100_;
  assign _102_ = _094_ | _096_;
  assign _103_ = _099_ | _102_;
  assign _104_ = _101_ | _103_;
  assign _105_ = _093_ | _104_;
  assign Y[5] = _091_ | _105_;
  assign _106_ = _157_ & _191_;
  assign _107_ = ~_106_;
  assign _108_ = _192_ & _196_;
  assign _109_ = _107_ & _108_;
  assign _110_ = _157_ ^ _208_;
  assign _111_ = _003_ & _110_;
  assign _112_ = _156_ & _009_;
  assign _113_ = _157_ & _045_;
  assign _114_ = A[7] & _011_;
  assign _115_ = A[5] & _027_;
  assign _116_ = _114_ | _115_;
  assign _117_ = _155_ & _017_;
  assign _118_ = _148_ & _014_;
  assign _119_ = _112_ | _118_;
  assign _120_ = _117_ | _119_;
  assign _121_ = _113_ | _116_;
  assign _122_ = _120_ | _121_;
  assign _123_ = _111_ | _122_;
  assign Y[6] = _109_ | _123_;
  assign _124_ = _153_ & _193_;
  assign _125_ = ~_124_;
  assign _126_ = _197_ & _125_;
  assign _127_ = _153_ ^ _000_;
  assign _128_ = _003_ & _127_;
  assign _129_ = _149_ & _014_;
  assign _130_ = A[6] & _027_;
  assign _131_ = _153_ & _045_;
  assign _132_ = _151_ & _017_;
  assign _133_ = _152_ & _009_;
  assign _134_ = _129_ | _132_;
  assign _135_ = _131_ | _133_;
  assign _136_ = _130_ | _135_;
  assign _137_ = _134_ | _136_;
  assign _138_ = _128_ | _137_;
  assign Y[7] = _126_ | _138_;
endmodule

projects/alu8_rtl_to_gds/tb/alu8_tb.v
`timescale 1ns/1ps

module alu8_tb;

reg [7:0] A;
reg [7:0] B;
reg [2:0] OP;

wire [7:0] Y;
wire CARRY;

alu8 uut (
    .A(A),
    .B(B),
    .OP(OP),
    .Y(Y),
    .CARRY(CARRY)
);

initial begin

    $dumpfile("alu8.vcd");
    $dumpvars(0, alu8_tb);

    $display("----- 8-bit ALU TEST -----");

    A = 8'd10;
    B = 8'd5;

    OP = 3'b000;
    #10;
    $display("ADD : A=%d B=%d Y=%d CARRY=%b", A, B, Y, CARRY);

    OP = 3'b001;
    #10;
    $display("SUB : A=%d B=%d Y=%d CARRY=%b", A, B, Y, CARRY);

    OP = 3'b010;
    #10;
    $display("AND : A=%d B=%d Y=%d", A, B, Y);

    OP = 3'b011;
    #10;
    $display("OR  : A=%d B=%d Y=%d", A, B, Y);

    OP = 3'b100;
    #10;
    $display("XOR : A=%d B=%d Y=%d", A, B, Y);

    OP = 3'b101;
    #10;
    $display("NOT : A=%d Y=%d", A, Y);

    OP = 3'b110;
    #10;
    $display("SHL : A=%d Y=%d", A, Y);

    OP = 3'b111;
    #10;
    $display("SHR : A=%d Y=%d", A, Y);

    $display("--------------------------");

    $finish;
end

endmodule

projects/alu8_rtl_to_gds/alu8.vcd
$date
	Wed Sep 16 16:20:08 2026
$end
$version
	Icarus Verilog
$end
$timescale
	1ps
$end
$scope module alu8_tb $end
$var wire 8 ! Y [7:0] $end
$var wire 1 " CARRY $end
$var reg 8 # A [7:0] $end
$var reg 8 $ B [7:0] $end
$var reg 3 % OP [2:0] $end
$scope module uut $end
$var wire 8 & A [7:0] $end
$var wire 8 ' B [7:0] $end
$var wire 3 ( OP [2:0] $end
$var reg 1 " CARRY $end
$var reg 8 ) Y [7:0] $end
$upscope $end
$upscope $end
$enddefinitions $end
$comment Show the parameter values. $end
$dumpall
$end
#0
$dumpvars
b1111 )
b0 (
b101 '
b1010 &
b0 %
b101 $
b1010 #
0"
b1111 !
$end
#10000
b101 !
b101 )
b1 %
b1 (
#20000
b0 !
b0 )
b10 %
b10 (
#30000
b1111 !
b1111 )
b11 %
b11 (
#40000
b1111 !
b1111 )
b100 %
b100 (
#50000
b11110101 !
b11110101 )
b101 %
b101 (
#60000
b10100 !
b10100 )
b110 %
b110 (
#70000
b101 !
b101 )
b111 %
b111 (
