projects/uart_tx_rtl_to_gds/rtl/uart_tx.v
module uart_tx #(
    parameter CLK_FREQ  = 50000000,
    parameter BAUD_RATE = 115200
)(
    input  wire       clk,
    input  wire       rst,
    input  wire       tx_start,
    input  wire [7:0] tx_data,
    output reg        tx,
    output reg        busy
);

localparam integer CLKS_PER_BIT = CLK_FREQ / BAUD_RATE;

reg [15:0] baud_counter;
reg [3:0]  bit_index;
reg [9:0]  tx_shift;

always @(posedge clk) begin

    if (rst) begin
        tx           <= 1'b1;
        busy         <= 1'b0;
        baud_counter <= 16'd0;
        bit_index    <= 4'd0;
        tx_shift     <= 10'b1111111111;
    end

    else begin

        if (tx_start && !busy) begin

            tx_shift <= {1'b1, tx_data, 1'b0};
            busy <= 1'b1;
            baud_counter <= 16'd0;
            bit_index <= 4'd0;
            tx <= 1'b0;

        end

        else if (busy) begin

            if (baud_counter == CLKS_PER_BIT - 1) begin

                baud_counter <= 16'd0;

                if (bit_index == 9) begin
                    busy <= 1'b0;
                    tx <= 1'b1;
                    bit_index <= 4'd0;
                end

                else begin
                    bit_index <= bit_index + 1'b1;
                    tx_shift <= tx_shift >> 1;
                    tx <= tx_shift[1];
                end

            end

            else begin
                baud_counter <= baud_counter + 1'b1;
            end

        end

    end
end

endmodule

projects/uart_tx_rtl_to_gds/tb/uart_tx_tb.v
`timescale 1ns/1ps

module uart_tx_tb;

reg clk;
reg rst;
reg tx_start;
reg [7:0] tx_data;

wire tx;
wire busy;

uart_tx #(
    .CLK_FREQ(1000000),
    .BAUD_RATE(100000)
) uut (
    .clk(clk),
    .rst(rst),
    .tx_start(tx_start),
    .tx_data(tx_data),
    .tx(tx),
    .busy(busy)
);

always #5 clk = ~clk;

initial begin

    $dumpfile("uart_tx.vcd");
    $dumpvars(0, uart_tx_tb);

    clk = 0;
    rst = 1;
    tx_start = 0;
    tx_data = 8'h55;

    #50;

    rst = 0;

    #20;

    tx_start = 1;
    #10;
    tx_start = 0;

    wait(!busy);

    #100;

    $finish;

end

endmodule

projects/uart_tx_rtl_to_gds/uart_tx.vcd
$date
	Wed Sep 16 17:24:14 2026
$end
$version
	Icarus Verilog
$end
$timescale
	1ps
$end
$scope module uart_tx_tb $end
$var wire 1 ! tx $end
$var wire 1 " busy $end
$var reg 1 # clk $end
$var reg 1 $ rst $end
$var reg 8 % tx_data [7:0] $end
$var reg 1 & tx_start $end
$scope module uut $end
$var wire 1 # clk $end
$var wire 1 $ rst $end
$var wire 8 ' tx_data [7:0] $end
$var wire 1 & tx_start $end
$var parameter 32 ( BAUD_RATE $end
$var parameter 32 ) CLKS_PER_BIT $end
$var parameter 32 * CLK_FREQ $end
$var reg 16 + baud_counter [15:0] $end
$var reg 4 , bit_index [3:0] $end
$var reg 1 " busy $end
$var reg 1 ! tx $end
$var reg 10 - tx_shift [9:0] $end
$upscope $end
$upscope $end
$enddefinitions $end
$comment Show the parameter values. $end
$dumpall
b11110100001001000000 *
b1010 )
b11000011010100000 (
$end
#0
$dumpvars
bx -
bx ,
bx +
b1010101 '
0&
b1010101 %
1$
0#
x"
x!
$end
#5000
b1111111111 -
b0 ,
b0 +
0"
1!
1#
#10000
0#
#15000
1#
#20000
0#
#25000
1#
#30000
0#
#35000
1#
#40000
0#
#45000
1#
#50000
0#
0$
#55000
1#
#60000
0#
#65000
1#
#70000
0#
1&
#75000
0!
1"
b1010101010 -
1#
#80000
0#
0&
#85000
b1 +
1#
#90000
0#
#95000
b10 +
1#
#100000
0#
#105000
b11 +
1#
#110000
0#
#115000
b100 +
1#
#120000
0#
#125000
b101 +
1#
#130000
0#
#135000
b110 +
1#
#140000
0#
#145000
b111 +
1#
#150000
0#
#155000
b1000 +
1#
#160000
0#
#165000
b1001 +
1#
#170000
0#
#175000
1!
b101010101 -
b1 ,
b0 +
1#
#180000
0#
#185000
b1 +
1#
#190000
0#
#195000
b10 +
1#
#200000
0#
#205000
b11 +
1#
#210000
0#
#215000
b100 +
1#
#220000
0#
#225000
b101 +
1#
#230000
0#
#235000
b110 +
1#
#240000
0#
#245000
b111 +
1#
#250000
0#
#255000
b1000 +
1#
#260000
0#
#265000
b1001 +
1#
#270000
0#
#275000
0!
b10101010 -
b10 ,
b0 +
1#
#280000
0#
#285000
b1 +
1#
#290000
0#
#295000
b10 +
1#
#300000
0#
#305000
b11 +
1#
#310000
0#
#315000
b100 +
1#
#320000
0#
#325000
b101 +
1#
#330000
0#
#335000
b110 +
1#
#340000
0#
#345000
b111 +
1#
#350000
0#
#355000
b1000 +
1#
#360000
0#
#365000
b1001 +
1#
#370000
0#
#375000
1!
b1010101 -
b11 ,
b0 +
1#
#380000
0#
#385000
b1 +
1#
#390000
0#
#395000
b10 +
1#
#400000
0#
#405000
b11 +
1#
#410000
0#
#415000
b100 +
1#
#420000
0#
#425000
b101 +
1#
#430000
0#
#435000
b110 +
1#
#440000
0#
#445000
b111 +
1#
#450000
0#
#455000
b1000 +
1#
#460000
0#
#465000
b1001 +
1#
#470000
0#
#475000
0!
b101010 -
b100 ,
b0 +
1#
#480000
0#
#485000
b1 +
1#
#490000
0#
#495000
b10 +
1#
#500000
0#
#505000
b11 +
1#
#510000
0#
#515000
b100 +
1#
#520000
0#
#525000
b101 +
1#
#530000
0#
#535000
b110 +
1#
#540000
0#
#545000
b111 +
1#
#550000
0#
#555000
b1000 +
1#
#560000
0#
#565000
b1001 +
1#
#570000
0#
#575000
1!
b10101 -
b101 ,
b0 +
1#
#580000
0#
#585000
b1 +
1#
#590000
0#
#595000
b10 +
1#
#600000
0#
#605000
b11 +
1#
#610000
0#
#615000
b100 +
1#
#620000
0#
#625000
b101 +
1#
#630000
0#
#635000
b110 +
1#
#640000
0#
#645000
b111 +
1#
#650000
0#
#655000
b1000 +
1#
#660000
0#
#665000
b1001 +
1#
#670000
0#
#675000
0!
b1010 -
b110 ,
b0 +
1#
#680000
0#
#685000
b1 +
1#
#690000
0#
#695000
b10 +
1#
#700000
0#
#705000
b11 +
1#
#710000
0#
#715000
b100 +
1#
#720000
0#
#725000
b101 +
1#
#730000
0#
#735000
b110 +
1#
#740000
0#
#745000
b111 +
1#
#750000
0#
#755000
b1000 +
1#
#760000
0#
#765000
b1001 +
1#
#770000
0#
#775000
1!
b101 -
b111 ,
b0 +
1#
#780000
0#
#785000
b1 +
1#
#790000
0#
#795000
b10 +
1#
#800000
0#
#805000
b11 +
1#
#810000
0#
#815000
b100 +
1#
#820000
0#
#825000
b101 +
1#
#830000
0#
#835000
b110 +
1#
#840000
0#
#845000
b111 +
1#
#850000
0#
#855000
b1000 +
1#
#860000
0#
#865000
b1001 +
1#
#870000
0#
#875000
0!
b10 -
b1000 ,
b0 +
1#
#880000
0#
#885000
b1 +
1#
#890000
0#
#895000
b10 +
1#
#900000
0#
#905000
b11 +
1#
#910000
0#
#915000
b100 +
1#
#920000
0#
#925000
b101 +
1#
#930000
0#
#935000
b110 +
1#
#940000
0#
#945000
b111 +
1#
#950000
0#
#955000
b1000 +
1#
#960000
0#
#965000
b1001 +
1#
#970000
0#
#975000
1!
b1 -
b1001 ,
b0 +
1#
#980000
0#
#985000
b1 +
1#
#990000
0#
#995000
b10 +
1#
#1000000
0#
#1005000
b11 +
1#
#1010000
0#
#1015000
b100 +
1#
#1020000
0#
#1025000
b101 +
1#
#1030000
0#
#1035000
b110 +
1#
#1040000
0#
#1045000
b111 +
1#
#1050000
0#
#1055000
b1000 +
1#
#1060000
0#
#1065000
b1001 +
1#
#1070000
0#
#1075000
b0 ,
0"
b0 +
1#
